project/GoogleDriveV3.py
project/__init__.py
project/mail.py
project/notification-email.html
project/plugin.py
project/spreadsheet.py
project/user_provision.py
project/plugins/__init__.py
project/plugins/artifactory/__init__.py
project/plugins/aws/__init__.py
project/plugins/azure/__init__.py
project/plugins/bitbucket/__init__.py
project/plugins/jira/__init__.py
project/plugins/papertrail/__init__.py
project/plugins/slack/__init__.py
uptool-1.3.2.dist-info/DESCRIPTION.rst
uptool-1.3.2.dist-info/METADATA
uptool-1.3.2.dist-info/RECORD
uptool-1.3.2.dist-info/WHEEL
uptool-1.3.2.dist-info/entry_points.txt
uptool-1.3.2.dist-info/metadata.json
uptool-1.3.2.dist-info/top_level.txt
