Metadata-Version: 2.0
Name: uptool
Version: 1.3.2
Summary: The User Provisioning Tool (UP Tool) can add or remove users from multiple web services with desired permissions and notify new user. Useful when a service does not support single sign-on or the plan cost to get single sign-on is prohibitivly expensive
Home-page: https://www.signiant.com
Author: UNKNOWN
Author-email: devops@signiant.com
License: MIT
Platform: UNKNOWN
Requires-Dist: azure (>=2.0.0)
Requires-Dist: msrest (>=0.5.0)
Requires-Dist: azure-common (>=1.1.14)
Requires-Dist: pytz (>=2018.3)
Requires-Dist: jenkinsapi (>=0.2.23)
Requires-Dist: paramiko (>=2.4.0)
Requires-Dist: botocore (>=1.10.50)
Requires-Dist: lxml (>=4.2.3)
Requires-Dist: requests (>=2.4.3)
Requires-Dist: boto3 (>=1.5.20)
Requires-Dist: msrestazure (>=0.4.21)
Requires-Dist: PyYAML (>=3.12)
Requires-Dist: beautifulsoup4 (>=4.6.0)
Requires-Dist: keyring (>=11.0.0)
Requires-Dist: oauth2client (>=3.0.0)
Requires-Dist: google-api-python-client (>=1.4.2)
Requires-Dist: httplib2 (>=0.9.1)
Requires-Dist: setuptools (>=38.5.1)
Requires-Dist: six (>=1.7)
Requires-Dist: nose (>=1.3.0)
Requires-Dist: tornado (>=4.5.1)
